AnyCAD/AnyCAD.Common.Core.dll
AnyCAD/AnyCAD.Common.GLFW.dll
AnyCAD/AnyCAD.Common.Gcs.dll
AnyCAD/AnyCAD.Common.Glad.dll
AnyCAD/AnyCAD.Common.SDL2.dll
AnyCAD/AnyCAD.Common.Zip.dll
AnyCAD/AnyCAD.Data.App.dll
AnyCAD/AnyCAD.Data.Kernel.dll
AnyCAD/AnyCAD.Data.Sketch.dll
AnyCAD/AnyCAD.Data.View.dll
AnyCAD/AnyCAD.Geometry.Areapath.dll
AnyCAD/AnyCAD.Geometry.Builder.dll
AnyCAD/AnyCAD.Geometry.Kernel.dll
AnyCAD/AnyCAD.Geometry.Modeling.dll
AnyCAD/AnyCAD.Geometry.View.dll
AnyCAD/AnyCAD.Graphics.Asset.dll
AnyCAD/AnyCAD.Graphics.Data.dll
AnyCAD/AnyCAD.Graphics.Gui.dll
AnyCAD/AnyCAD.Graphics.Kernel.dll
AnyCAD/AnyCAD.Graphics.Mesh.dll
AnyCAD/AnyCAD.Graphics.Renderer.dll
AnyCAD/AnyCAD.Graphics.View.dll
AnyCAD/AnyCAD.Graphics.Window.dll
AnyCAD/AnyCAD.Interop.DXF.dll
AnyCAD/AnyCAD.Interop.Geometry.dll
AnyCAD/AnyCAD.Interop.Graphics.dll
AnyCAD/AnyCAD.Modeling.Data.dll
AnyCAD/AnyCAD.PointCloud.Data.dll
AnyCAD/AnyCAD.PointCloud.Kernel.dll
AnyCAD/AnyCAD.ScriptPy.Kernel.dll
AnyCAD/AnyCAD.Simulate.Data.dll
AnyCAD/AnyCAD.Simulate.FEM.dll
AnyCAD/AnyCAD.Simulate.Kernel.dll
AnyCAD/AnyCAD.Simulate.Physics.dll
AnyCAD/AnyCAD.Simulate.Robot.dll
AnyCAD/PyAnyCAD.py
AnyCAD/PyAnyCore.py
AnyCAD/PyAnyInit.py
AnyCAD/PyAnyQt.py
AnyCAD/PyAnyView.py
AnyCAD/TKBO.dll
AnyCAD/TKBRep.dll
AnyCAD/TKBin.dll
AnyCAD/TKBinL.dll
AnyCAD/TKBinTObj.dll
AnyCAD/TKBinXCAF.dll
AnyCAD/TKBool.dll
AnyCAD/TKCAF.dll
AnyCAD/TKCDF.dll
AnyCAD/TKExpress.dll
AnyCAD/TKFeat.dll
AnyCAD/TKFillet.dll
AnyCAD/TKG2d.dll
AnyCAD/TKG3d.dll
AnyCAD/TKGeomAlgo.dll
AnyCAD/TKGeomBase.dll
AnyCAD/TKHLR.dll
AnyCAD/TKIGES.dll
AnyCAD/TKLCAF.dll
AnyCAD/TKMath.dll
AnyCAD/TKMesh.dll
AnyCAD/TKMeshVS.dll
AnyCAD/TKOffset.dll
AnyCAD/TKPrim.dll
AnyCAD/TKRWMesh.dll
AnyCAD/TKSTEP.dll
AnyCAD/TKSTEP209.dll
AnyCAD/TKSTEPAttr.dll
AnyCAD/TKSTEPBase.dll
AnyCAD/TKSTL.dll
AnyCAD/TKService.dll
AnyCAD/TKShHealing.dll
AnyCAD/TKStd.dll
AnyCAD/TKStdL.dll
AnyCAD/TKTObj.dll
AnyCAD/TKTopAlgo.dll
AnyCAD/TKV3d.dll
AnyCAD/TKVCAF.dll
AnyCAD/TKVRML.dll
AnyCAD/TKXCAF.dll
PyAnyCAD-2024.4.1.dist-info/METADATA
PyAnyCAD-2024.4.1.dist-info/WHEEL
PyAnyCAD-2024.4.1.dist-info/top_level.txt
PyAnyCAD-2024.4.1.dist-info/RECORD
