Metadata-Version: 2.1
Name: PyAnyCAD
Version: 2024.4.1
Summary: The 3D Graphics/Geometry library for Python Developer
Home-page: http://www.anycad.cn
Author: AnyCAD
Author-email: anycad@anycad.cn
License: AnyCAD License
Keywords: AnyCAD,Graphics,OpenGL,Geometry,Modeling
Platform: win64
